odoo/addons/website_sale_charge_payment_fee/README.rst
odoo/addons/website_sale_charge_payment_fee/__init__.py
odoo/addons/website_sale_charge_payment_fee/__manifest__.py
odoo/addons/website_sale_charge_payment_fee/controllers/__init__.py
odoo/addons/website_sale_charge_payment_fee/controllers/main.py
odoo/addons/website_sale_charge_payment_fee/i18n/es.po
odoo/addons/website_sale_charge_payment_fee/i18n/es_AR.po
odoo/addons/website_sale_charge_payment_fee/i18n/it.po
odoo/addons/website_sale_charge_payment_fee/i18n/website_sale_charge_payment_fee.pot
odoo/addons/website_sale_charge_payment_fee/models/__init__.py
odoo/addons/website_sale_charge_payment_fee/models/payment_acquirer.py
odoo/addons/website_sale_charge_payment_fee/models/sale_order.py
odoo/addons/website_sale_charge_payment_fee/models/sale_order_line.py
odoo/addons/website_sale_charge_payment_fee/readme/CONFIGURE.rst
odoo/addons/website_sale_charge_payment_fee/readme/CONTRIBUTORS.rst
odoo/addons/website_sale_charge_payment_fee/readme/DESCRIPTION.rst
odoo/addons/website_sale_charge_payment_fee/static/description/icon.png
odoo/addons/website_sale_charge_payment_fee/static/description/index.html
odoo/addons/website_sale_charge_payment_fee/static/src/js/website_sale_fee.js
odoo/addons/website_sale_charge_payment_fee/static/tests/tours/website_sale_fee_tour.js
odoo/addons/website_sale_charge_payment_fee/tests/__init__.py
odoo/addons/website_sale_charge_payment_fee/tests/test_website_sale_fee.py
odoo/addons/website_sale_charge_payment_fee/views/payment_acquirer_views.xml
odoo/addons/website_sale_charge_payment_fee/views/website_sale_templates.xml
odoo14_addon_website_sale_charge_payment_fee-14.0.1.0.1.dev8.dist-info/METADATA
odoo14_addon_website_sale_charge_payment_fee-14.0.1.0.1.dev8.dist-info/WHEEL
odoo14_addon_website_sale_charge_payment_fee-14.0.1.0.1.dev8.dist-info/top_level.txt
odoo14_addon_website_sale_charge_payment_fee-14.0.1.0.1.dev8.dist-info/RECORD
