Metadata-Version: 2.1
Name: odoo14-addon-website_sale_charge_payment_fee
Version: 14.0.1.0.1.dev8
Summary: Payment fee charged to customer
Home-page: https://github.com/OCA/e-commerce
Author: Agile Business Group, AITIC S.A.S, Quartile Limited, Studio73, Odoo Community Association (OCA)
Author-email: support@odoo-community.org
License: LGPL-3
Classifier: Programming Language :: Python
Classifier: Framework :: Odoo
Classifier: Framework :: Odoo :: 14.0
Classifier: License :: OSI Approved :: GNU Lesser General Public License v3 (LGPLv3)
Requires-Python: >=3.6
Requires-Dist: odoo<14.1dev,>=14.0a
